{"name":"Python0","tagline":"Introduction to programming with Python course in TUES","body":"# python0\r\n\r\n[![Gitter](https://badges.gitter.im/Join%20Chat.svg)](https://gitter.im/YAtOff/python0?utm_source=badge&utm_medium=badge&utm_campaign=pr-badge&utm_content=badge)\r\n\r\n### Как да предам домашното си\r\n\r\n1. Ако нямате Google акаунт - създайте си\r\n2. Отворете [Google Drive] (https://drive.google.com)\r\n3. Създайте папка кръстена `homework{{номер в клас}}`, напр. ако сте номер 1 - `homework1`\r\n4. Споделете папката с `yavor.atov@gmail.com`\r\n5. Вътре в папката създайте папки за отделните седмици, за които има домашнo - `week2`, `week4`, ...\r\n6. Кръщавайте файловете така, както е посочено във задачата.\r\n   Задача със грешно име на файл няма да бъде проверявана.\r\n7. Качете файловете във съответната папка\r\n\r\n### Полезни връзки за курса\r\n\r\n - [Списък на класа] (https://docs.google.com/spreadsheets/d/1rZMFnNCayTSeqSQGRyU7s5a9vK7-jYHsSyEf8dOWL4A/edit?usp=sharing)\r\n - [Как да инсталираме Python] (http://www.howtogeek.com/197947/how-to-install-python-on-windows/)\r\n - [Онлайн среда] (https://trinket.io) - тук може решавате домашните си, ако не ста; може да използвате и `turtle`\r\n - [Онлайн среда] (https://repl.it) - тук може решавате домашните си, ако не ста\r\n   успяли да инсталирате Python\r\n - Книги:\r\n    - [Python for kids] (http://www.it-ebooks.info/book/2226/)\r\n    - [Practical programming, 2nd edition] (http://www.it-ebooks.info/book/3751/)\r\n\r\n\r\n### Препоръчани тексотви редактори\r\n- [Sublime Text 3] (http://www.sublimetext.com/3)\r\n- [Atom] (https://atom.io/)\r\n- [Notepad++] (https://notepad-plus-plus.org/)\r\n\r\n\r\n### Допълнителни курсове\r\n - [How to Think Like a Computer Scientis] (http://interactivepython.org/runestone/static/thinkcspy/index.html)\r\n  Глави:\r\n  - General Introduction\r\n  - Simple Python Data\r\n  - Debugging Interlude\r\n  - Python Turtle Graphics\r\n  - Functions\r\n  - Selection\r\n  - More About Iteration\r\n  - Lists\r\n - [A Visual Introduction to Python] (https://hourofpython.trinket.io/a-visual-introduction-to-python)\r\n","google":"","note":"Don't delete this file! It's used internally to help with page regeneration."}